flumes_fuse/__init__.py
flumes_fuse/fs.py
flumes_fuse/options.py
flumes_fuse/path.py
flumes_fuse-0.1.2.dist-info/entry_points.txt
flumes_fuse-0.1.2.dist-info/LICENSE.LGPL
flumes_fuse-0.1.2.dist-info/WHEEL
flumes_fuse-0.1.2.dist-info/METADATA
flumes_fuse-0.1.2.dist-info/RECORD
