Metadata-Version: 2.1
Name: flumes-fuse
Version: 0.1.2
Summary: Tool that generates a userspace filesystem off of a flumes created database
License: LGPL-2.1-only
Author: Jorge Zapata
Author-email: jorgeluis.zapata@gmail.com
Maintainer: Michalis Dimopoulos
Maintainer-email: mdimopoulos@fluendo.com
Requires-Python: >=3.9,<4.0
Classifier: License :: OSI Approved
Classifier: Programming Language :: Python :: 3
Classifier: Programming Language :: Python :: 3.10
Classifier: Programming Language :: Python :: 3.9
Requires-Dist: SQLAlchemy (>=1.4.26,<2.0.0)
Requires-Dist: flumes (>=0.1.4,<0.2.0)
Requires-Dist: fuse-python (>=1.0.4,<2.0.0)
